odoo8_addon_contract_recurring_invoicing_marker-8.0.1.0.0.99.dev18-py3.8-nspkg.pth
odoo_addons/contract_recurring_invoicing_marker/README.rst
odoo_addons/contract_recurring_invoicing_marker/__init__.py
odoo_addons/contract_recurring_invoicing_marker/__openerp__.py
odoo_addons/contract_recurring_invoicing_marker/i18n/ca.po
odoo_addons/contract_recurring_invoicing_marker/i18n/contract_recurring_invoicing_marker.pot
odoo_addons/contract_recurring_invoicing_marker/i18n/de.po
odoo_addons/contract_recurring_invoicing_marker/i18n/el_GR.po
odoo_addons/contract_recurring_invoicing_marker/i18n/es.po
odoo_addons/contract_recurring_invoicing_marker/i18n/es_MX.po
odoo_addons/contract_recurring_invoicing_marker/i18n/fi.po
odoo_addons/contract_recurring_invoicing_marker/i18n/fr.po
odoo_addons/contract_recurring_invoicing_marker/i18n/pt_BR.po
odoo_addons/contract_recurring_invoicing_marker/i18n/sk_SK.po
odoo_addons/contract_recurring_invoicing_marker/i18n/sl.po
odoo_addons/contract_recurring_invoicing_marker/i18n/zh_CN.po
odoo_addons/contract_recurring_invoicing_marker/models/__init__.py
odoo_addons/contract_recurring_invoicing_marker/models/account_analytic_account.py
odoo_addons/contract_recurring_invoicing_marker/static/description/icon.png
odoo_addons/contract_recurring_invoicing_marker/static/description/icon.svg
odoo_addons/contract_recurring_invoicing_marker/tests/__init__.py
odoo_addons/contract_recurring_invoicing_marker/tests/test_contract_recurring_invoicing_marker.py
odoo_addons/contract_recurring_invoicing_marker/views/account_analytic_account_view.xml
odoo8_addon_contract_recurring_invoicing_marker-8.0.1.0.0.99.dev18.dist-info/METADATA
odoo8_addon_contract_recurring_invoicing_marker-8.0.1.0.0.99.dev18.dist-info/WHEEL
odoo8_addon_contract_recurring_invoicing_marker-8.0.1.0.0.99.dev18.dist-info/namespace_packages.txt
odoo8_addon_contract_recurring_invoicing_marker-8.0.1.0.0.99.dev18.dist-info/top_level.txt
odoo8_addon_contract_recurring_invoicing_marker-8.0.1.0.0.99.dev18.dist-info/RECORD
